pickerxl/__init__.py
pickerxl/pickerxl.py
pickerxl/model/__init__.py
pickerxl/model/large.ckpt
pickerxl-0.2.3.dist-info/licenses/LICENSE
pickerxl-0.2.3.dist-info/METADATA
pickerxl-0.2.3.dist-info/WHEEL
pickerxl-0.2.3.dist-info/top_level.txt
pickerxl-0.2.3.dist-info/RECORD
