Metadata-Version: 2.4
Name: pickerxl
Version: 0.2.3
Summary: PickerXL is a large deep learning model to measure arrival times from noisy seismic signals.
Author-email: "Chengping Chai, Derek Rose, Scott Stewart, Nathan Martindale, Mark Adams, Lisa Linville, Christopher Stanley, Anibely Torres Polanco and Philip Bingham" <chaic@ornl.gov>
License-Expression: GPL-3.0-or-later
Project-URL: Homepage, https://github.com/ornl/picker-xl
Classifier: Intended Audience :: Science/Research
Classifier: Topic :: Scientific/Engineering
Classifier: Programming Language :: Python :: 3
Classifier: Operating System :: OS Independent
Requires-Python: >=3.11
License-File: LICENSE
Requires-Dist: torch>=2.3.0
Requires-Dist: numpy>=1.26.4
Requires-Dist: lightning>=2.2.4
Requires-Dist: h5py>=3.11.0
Requires-Dist: matplotlib>=3.8.0
Provides-Extra: development
Requires-Dist: flake8; extra == "development"
Requires-Dist: black; extra == "development"
Requires-Dist: pre-commit; extra == "development"
Dynamic: license-file
